itk/PrincipalComponentsAnalysisPython.py
itk/_PrincipalComponentsAnalysisPython.so
itk/itkGaussianDistanceKernelPython.py
itk/Configuration/PrincipalComponentsAnalysisConfig.py
itk_principalcomponentsanalysis-1.0.0.dist-info/LICENSE
itk_principalcomponentsanalysis-1.0.0.dist-info/METADATA
itk_principalcomponentsanalysis-1.0.0.dist-info/WHEEL
itk_principalcomponentsanalysis-1.0.0.dist-info/top_level.txt
itk_principalcomponentsanalysis-1.0.0.dist-info/RECORD
